MANIFEST.in
auth_signup_data.xml
res_config.xml
res_users_view.xml
setup.py
./__init__.py
./__openerp__.py
./res_config.py
./res_users.py
./controllers/__init__.py
./controllers/main.py
i18n/ar.po
i18n/auth_signup.pot
i18n/cs.po
i18n/de.po
i18n/en_GB.po
i18n/es.po
i18n/es_CO.po
i18n/fr.po
i18n/hr.po
i18n/hu.po
i18n/it.po
i18n/lt.po
i18n/mk.po
i18n/mn.po
i18n/nb.po
i18n/nl.po
i18n/pl.po
i18n/pt.po
i18n/pt_BR.po
i18n/ro.po
i18n/ru.po
i18n/sl.po
i18n/tr.po
i18n/vi.po
i18n/zh_CN.po
i18n/zh_TW.po
openerp_auth_signup.egg-info/PKG-INFO
openerp_auth_signup.egg-info/SOURCES.txt
openerp_auth_signup.egg-info/dependency_links.txt
openerp_auth_signup.egg-info/requires.txt
openerp_auth_signup.egg-info/top_level.txt
static/src/js/auth_signup.js
static/src/xml/auth_signup.xml